SiDoLa/SiDoLaNS.py
SiDoLa/__init__.py
SiDoLa-0.0.3.dist-info/LICENSE
SiDoLa-0.0.3.dist-info/METADATA
SiDoLa-0.0.3.dist-info/WHEEL
SiDoLa-0.0.3.dist-info/top_level.txt
SiDoLa-0.0.3.dist-info/RECORD
