Metadata-Version: 2.1
Name: SiDoLa
Version: 0.0.3
Summary: SiDoLa (prounounced like Do Re Mi) is short for 'Simulate Don't Label'. These are a set of tools to create nervous system simulations and used the resulting models to extract image-based features from biological sections of nervous system tissue.
Author-email: William Buchser <wbuchser@wustl.edu>, Lina Ali <linakali@wustl.edu>
Project-URL: Homepage, https://gitlab.com/buchserlab/sidola-ns
Project-URL: Issues, https://gitlab.com/buchserlab/sidola-ns/-/issues
Classifier: Programming Language :: Python :: 3
Classifier: License :: OSI Approved :: MIT License
Classifier: Operating System :: OS Independent
Requires-Python: >=3.8
License-File: LICENSE
